README.md
setup.cfg
setup.py
wows_api/__init__.py
wows_api/wargaming_api.py
wows_api.egg-info/PKG-INFO
wows_api.egg-info/SOURCES.txt
wows_api.egg-info/dependency_links.txt
wows_api.egg-info/requires.txt
wows_api.egg-info/top_level.txt