Metadata-Version: 1.2
Name: wows-api
Version: 0.2
Summary: Работа с api world of warship
Home-page: https://github.com/pachkun/wows_api
Author: pachkun
Author-email: pachkunishka@gmail.com
License: UNKNOWN
Platform: UNKNOWN
Requires-Python: >=3.6
